YayAPI/Yay.py
YayAPI/__init__.py
YayAPI-1.1.0.dist-info/METADATA
YayAPI-1.1.0.dist-info/WHEEL
YayAPI-1.1.0.dist-info/top_level.txt
YayAPI-1.1.0.dist-info/RECORD
