Metadata-Version: 2.1
Name: YayAPI
Version: 1.1.0
Summary: Unofficial api library for yay.space
Home-page: https://github.com/konn-konn/YayAPI
Download-URL: https://github.com/konn-konn/YayAPI
Author: Konn
Author-email: hello@konn.dev
Maintainer: Konn
Maintainer-email: hello@konn.dev
Requires-Dist: requests (>=2.25.1)
Requires-Dist: fake-useragent (>=1.1.1)
